ecglib/__init__.py
ecglib/data/__init__.py
ecglib/data/datasets.py
ecglib/data/ecg_record.py
ecglib/data/load_datasets.py
ecglib/models/__init__.py
ecglib/models/model_builder.py
ecglib/models/architectures/__init__.py
ecglib/models/architectures/cnn_tabular.py
ecglib/models/architectures/densenet1d.py
ecglib/models/architectures/model_types.py
ecglib/models/architectures/registred_models.py
ecglib/models/architectures/resnet1d.py
ecglib/models/architectures/tabular.py
ecglib/models/config/__init__.py
ecglib/models/config/model_configs.py
ecglib/models/config/registred_configs.py
ecglib/models/weights/__init__.py
ecglib/models/weights/checkpoint.py
ecglib/models/weights/model_weights_paths.yaml
ecglib/predict/__init__.py
ecglib/predict/predict.py
ecglib/preprocessing/__init__.py
ecglib/preprocessing/composition.py
ecglib/preprocessing/functional.py
ecglib/preprocessing/preprocess.py
ecglib-1.1.1.dist-info/LICENSE
ecglib-1.1.1.dist-info/METADATA
ecglib-1.1.1.dist-info/WHEEL
ecglib-1.1.1.dist-info/top_level.txt
ecglib-1.1.1.dist-info/RECORD
