Metadata-Version: 2.1
Name: ecglib
Version: 1.1.1
Summary: ECG library with pretrained models and tools for ECG analysis
Home-page: https://github.com/ispras/EcgLib
Author: Aram Avetisyan
Author-email: a.a.avetisyan@gmail.com
License: Apache License 2.0
Keywords: {"ecg analysis","pytorch","pretrained models","ecg preprocessing","ecg datasets"}
Platform: UNKNOWN
Requires-Python: >=3.6
License-File: LICENSE
Requires-Dist: PyWavelets (>=1.3.0)
Requires-Dist: ecg-plot (>=0.0.1)
Requires-Dist: fastai (>=2.7.10)
Requires-Dist: ipywidgets (>=7.6.5)
Requires-Dist: neurokit2 (>=0.2.2)
Requires-Dist: numpy (>=1.2)
Requires-Dist: omegaconf (>=2.3.0)
Requires-Dist: pandas (>=1.5.2)
Requires-Dist: pyyaml (>=6.0)
Requires-Dist: scipy (>=1.7.3)
Requires-Dist: torch (>=1.13.1)
Requires-Dist: tqdm (>=4.64.0)
Requires-Dist: wfdb (>=4.0.0)
